<?xml version="1.0" encoding="UTF-8" standalone="no"?><Oleada nombre="WAVE"><Dragones><Dragon Edad="901" Nombre="Paarthurnax" Rango="Comandant" Resistencia="3" Velocidad="3"/><Dragon Edad="907" Nombre="Thorn" Rango="Captain" Resistencia="2" Velocidad="3"/><Dragon Edad="917" Nombre="Alexstrasza" Rango="Captain" Resistencia="2" Velocidad="3"/><Dragon Edad="904" Nombre="Aurelion Sol" Rango="Captain" Resistencia="2" Velocidad="3"/><Dragon Edad="965" Nombre="Vel'Koz" Rango="Captain" Resistencia="2" Velocidad="3"/><Dragon Edad="965" Nombre="Ancalagon" Rango="Infantry" Resistencia="1" Velocidad="3"/><Dragon Edad="998" Nombre="Balerion" Rango="Infantry" Resistencia="1" Velocidad="3"/><Dragon Edad="947" Nombre="Chrysophylax" Rango="Infantry" Resistencia="1" Velocidad="3"/><Dragon Edad="956" Nombre="Quetzalcóatl" Rango="Infantry" Resistencia="1" Velocidad="3"/><Dragon Edad="968" Nombre="Kalameet" Rango="Infantry" Resistencia="1" Velocidad="3"/></Dragones></Oleada>